lilliepy_dir_router/__init__.py
lilliepy_dir_router/router.py
lilliepy_dir_router-10.0.1.dist-info/METADATA
lilliepy_dir_router-10.0.1.dist-info/WHEEL
lilliepy_dir_router-10.0.1.dist-info/top_level.txt
lilliepy_dir_router-10.0.1.dist-info/RECORD
